<?xml version="1.0" encoding="UTF-8" ?>
<!DOCTYPE mapper PUBLIC "-//mybatis.org//DTD Mapper 3.0//EN" "http://mybatis.org/dtd/mybatis-3-mapper.dtd" >
<mapper namespace="cn.com.realer.dao.generator.m.GabMBlockMapper" >
  <resultMap id="BaseResultMap" type="cn.com.realer.pojo.GabMBlock" >
    <!--
      WARNING - @mbggenerated
      This element is automatically generated by MyBatis Generator, do not modify.
    -->
    <id column="id" property="id" jdbcType="INTEGER" />
    <result column="name_" property="name" jdbcType="VARCHAR" />
    <result column="create_time" property="createTime" jdbcType="TIMESTAMP" />
    <result column="update_time" property="updateTime" jdbcType="TIMESTAMP" />
    <result column="isdelete" property="isdelete" jdbcType="SMALLINT" />
    <result column="model_id" property="modelId" jdbcType="INTEGER" />
    <result column="order_id" property="orderId" jdbcType="INTEGER" />
    <result column="icon" property="icon" jdbcType="VARCHAR" />
  </resultMap>
  <delete id="deleteByPrimaryKey" parameterType="java.lang.Integer" >
    <!--
      WARNING - @mbggenerated
      This element is automatically generated by MyBatis Generator, do not modify.
    -->
    delete from gab_m_block
    where id = #{id,jdbcType=INTEGER}
  </delete>
  <insert id="insert" parameterType="cn.com.realer.pojo.GabMBlock" useGeneratedKeys="true" keyProperty="id" >
    <!--
      WARNING - @mbggenerated
      This element is automatically generated by MyBatis Generator, do not modify.
    -->
    insert into gab_m_block (name_, create_time, update_time, 
      isdelete, model_id, order_id, 
      icon)
    values (#{name,jdbcType=VARCHAR}, #{createTime,jdbcType=TIMESTAMP}, #{updateTime,jdbcType=TIMESTAMP}, 
      #{isdelete,jdbcType=SMALLINT}, #{modelId,jdbcType=INTEGER}, #{orderId,jdbcType=INTEGER}, 
      #{icon,jdbcType=VARCHAR})
  </insert>
  <update id="updateByPrimaryKey" parameterType="cn.com.realer.pojo.GabMBlock" >
    <!--
      WARNING - @mbggenerated
      This element is automatically generated by MyBatis Generator, do not modify.
    -->
    update gab_m_block
    set name_ = #{name,jdbcType=VARCHAR},
      create_time = #{createTime,jdbcType=TIMESTAMP},
      update_time = #{updateTime,jdbcType=TIMESTAMP},
      isdelete = #{isdelete,jdbcType=SMALLINT},
      model_id = #{modelId,jdbcType=INTEGER},
      order_id = #{orderId,jdbcType=INTEGER},
      icon = #{icon,jdbcType=VARCHAR}
    where id = #{id,jdbcType=INTEGER}
  </update>
  <select id="selectByPrimaryKey" resultMap="BaseResultMap" parameterType="java.lang.Integer" >
    <!--
      WARNING - @mbggenerated
      This element is automatically generated by MyBatis Generator, do not modify.
    -->
    select id, name_, create_time, update_time, isdelete, model_id, order_id, icon
    from gab_m_block
    where id = #{id,jdbcType=INTEGER}
  </select>
  <select id="selectAll" resultMap="BaseResultMap" >
    <!--
      WARNING - @mbggenerated
      This element is automatically generated by MyBatis Generator, do not modify.
    -->
    select id, name_, create_time, update_time, isdelete, model_id, order_id, icon
    from gab_m_block
  </select>
</mapper>